{
  "info": {
    "name": { "firstname": "John", "lastname": "Doe", "title": "Dr" },
    "about": "Member & a Fellow of the Royal College of Pediatrics & Child Health (London)",
    "specialty": "Medical Oncology"
  },
  "insurance": [
    "Watania National Insurance Company",
    "Arab Orient Insurance Company (gig)",
    "Middle East Insurance Company",
    "MEDGULF"
  ],
  "rating": { "score": "4.73", "from_visitors_count": 194 },
  "reviews": {
    "name": "Sohib A.",
    "rating": 5,
    "review": "Thank you Dr. undefined for giving me the time to explain my case. Every session with him has been very satisfactory. He doesn't do things in a hurry, he is always precise patient and is very friendly as well.",
    "date": "Saturday, October 17th"
  },
  "schedule": [
    {
      "availability": {
        "label": "Thursday, August 25th",
        "month": "August",
        "year": "2022",
        "day": "Thursday",
        "date": "25-08-2022",
        "available": 6,
        "unavailable": 3,
        "total": 9
      },
      "unavailable": [
        { "from_unix": 1661439600, "to_unix": 1661443200 },
        { "from_unix": 1661421600, "to_unix": 1661425200 },
        { "from_unix": 1661446800, "to_unix": 1661450400 }
      ],
      "available": [
        { "from_unix": 1661414400, "to_unix": 1661432400 },
        { "from_unix": 1661436000, "to_unix": 1661450400 }
      ]
    },
    {
      "availability": {
        "label": "Friday, August 26th",
        "month": "August",
        "year": "2022",
        "day": "Friday",
        "date": "26-08-2022",
        "available": 6,
        "unavailable": 3,
        "total": 9
      },
      "unavailable": [
        { "from_unix": 1661526000, "to_unix": 1661529600 },
        { "from_unix": 1661533200, "to_unix": 1661536800 },
        { "from_unix": 1661511600, "to_unix": 1661515200 }
      ],
      "available": [
        { "from_unix": 1661500800, "to_unix": 1661518800 },
        { "from_unix": 1661522400, "to_unix": 1661536800 }
      ]
    },
    {
      "availability": {
        "label": "Saturday, August 27th",
        "month": "August",
        "year": "2022",
        "day": "Saturday",
        "date": "27-08-2022",
        "available": 8,
        "unavailable": 1,
        "total": 9
      },
      "unavailable": [{ "from_unix": 1661587200, "to_unix": 1661590800 }],
      "available": [
        { "from_unix": 1661587200, "to_unix": 1661605200 },
        { "from_unix": 1661608800, "to_unix": 1661623200 }
      ]
    },
    {
      "availability": {
        "label": "Sunday, August 28th",
        "month": "August",
        "year": "2022",
        "day": "Sunday",
        "date": "28-08-2022",
        "available": 8,
        "unavailable": 1,
        "total": 9
      },
      "unavailable": [{ "from_unix": 1661688000, "to_unix": 1661691600 }],
      "available": [
        { "from_unix": 1661673600, "to_unix": 1661691600 },
        { "from_unix": 1661695200, "to_unix": 1661709600 }
      ]
    },
    {
      "availability": {
        "label": "Monday, August 29th",
        "month": "August",
        "year": "2022",
        "day": "Monday",
        "date": "29-08-2022",
        "available": 5,
        "unavailable": 4,
        "total": 9
      },
      "unavailable": [
        { "from_unix": 1661760000, "to_unix": 1661763600 },
        { "from_unix": 1661763600, "to_unix": 1661767200 },
        { "from_unix": 1661788800, "to_unix": 1661792400 },
        { "from_unix": 1661788800, "to_unix": 1661792400 }
      ],
      "available": [
        { "from_unix": 1661760000, "to_unix": 1661778000 },
        { "from_unix": 1661781600, "to_unix": 1661796000 }
      ]
    },
    {
      "availability": {
        "label": "Tuesday, August 30th",
        "month": "August",
        "year": "2022",
        "day": "Tuesday",
        "date": "30-08-2022",
        "available": 7,
        "unavailable": 2,
        "total": 9
      },
      "unavailable": [
        { "from_unix": 1661878800, "to_unix": 1661882400 },
        { "from_unix": 1661860800, "to_unix": 1661864400 }
      ],
      "available": [
        { "from_unix": 1661846400, "to_unix": 1661864400 },
        { "from_unix": 1661868000, "to_unix": 1661882400 }
      ]
    },
    {
      "availability": {
        "label": "Wednesday, August 31st",
        "month": "August",
        "year": "2022",
        "day": "Wednesday",
        "date": "31-08-2022",
        "available": 7,
        "unavailable": 2,
        "total": 9
      },
      "unavailable": [
        { "from_unix": 1661958000, "to_unix": 1661961600 },
        { "from_unix": 1661940000, "to_unix": 1661943600 }
      ],
      "available": [
        { "from_unix": 1661932800, "to_unix": 1661950800 },
        { "from_unix": 1661954400, "to_unix": 1661968800 }
      ]
    },
    {
      "availability": {
        "label": "Thursday, September 1st",
        "month": "September",
        "year": "2022",
        "day": "Thursday",
        "date": "01-09-2022",
        "available": 7,
        "unavailable": 2,
        "total": 9
      },
      "unavailable": [
        { "from_unix": 1662022800, "to_unix": 1662026400 },
        { "from_unix": 1662033600, "to_unix": 1662037200 }
      ],
      "available": [
        { "from_unix": 1662019200, "to_unix": 1662037200 },
        { "from_unix": 1662040800, "to_unix": 1662055200 }
      ]
    },
    {
      "availability": {
        "label": "Friday, September 2nd",
        "month": "September",
        "year": "2022",
        "day": "Friday",
        "date": "02-09-2022",
        "available": 6,
        "unavailable": 3,
        "total": 9
      },
      "unavailable": [
        { "from_unix": 1662120000, "to_unix": 1662123600 },
        { "from_unix": 1662130800, "to_unix": 1662134400 },
        { "from_unix": 1662105600, "to_unix": 1662109200 }
      ],
      "available": [
        { "from_unix": 1662105600, "to_unix": 1662123600 },
        { "from_unix": 1662127200, "to_unix": 1662141600 }
      ]
    },
    {
      "availability": {
        "label": "Saturday, September 3rd",
        "month": "September",
        "year": "2022",
        "day": "Saturday",
        "date": "03-09-2022",
        "available": 9,
        "unavailable": 0,
        "total": 9
      },
      "unavailable": [],
      "available": [
        { "from_unix": 1662192000, "to_unix": 1662210000 },
        { "from_unix": 1662213600, "to_unix": 1662228000 }
      ]
    },
    {
      "availability": {
        "label": "Sunday, September 4th",
        "month": "September",
        "year": "2022",
        "day": "Sunday",
        "date": "04-09-2022",
        "available": 7,
        "unavailable": 2,
        "total": 9
      },
      "unavailable": [
        { "from_unix": 1662289200, "to_unix": 1662292800 },
        { "from_unix": 1662300000, "to_unix": 1662303600 }
      ],
      "available": [
        { "from_unix": 1662278400, "to_unix": 1662296400 },
        { "from_unix": 1662300000, "to_unix": 1662314400 }
      ]
    },
    {
      "availability": {
        "label": "Monday, September 5th",
        "month": "September",
        "year": "2022",
        "day": "Monday",
        "date": "05-09-2022",
        "available": 6,
        "unavailable": 3,
        "total": 9
      },
      "unavailable": [
        { "from_unix": 1662397200, "to_unix": 1662400800 },
        { "from_unix": 1662397200, "to_unix": 1662400800 },
        { "from_unix": 1662397200, "to_unix": 1662400800 }
      ],
      "available": [
        { "from_unix": 1662364800, "to_unix": 1662382800 },
        { "from_unix": 1662386400, "to_unix": 1662400800 }
      ]
    },
    {
      "availability": {
        "label": "Tuesday, September 6th",
        "month": "September",
        "year": "2022",
        "day": "Tuesday",
        "date": "06-09-2022",
        "available": 8,
        "unavailable": 1,
        "total": 9
      },
      "unavailable": [{ "from_unix": 1662451200, "to_unix": 1662454800 }],
      "available": [
        { "from_unix": 1662451200, "to_unix": 1662469200 },
        { "from_unix": 1662472800, "to_unix": 1662487200 }
      ]
    },
    {
      "availability": {
        "label": "Wednesday, September 7th",
        "month": "September",
        "year": "2022",
        "day": "Wednesday",
        "date": "07-09-2022",
        "available": 5,
        "unavailable": 4,
        "total": 9
      },
      "unavailable": [
        { "from_unix": 1662541200, "to_unix": 1662544800 },
        { "from_unix": 1662570000, "to_unix": 1662573600 },
        { "from_unix": 1662570000, "to_unix": 1662573600 },
        { "from_unix": 1662559200, "to_unix": 1662562800 }
      ],
      "available": [
        { "from_unix": 1662537600, "to_unix": 1662555600 },
        { "from_unix": 1662559200, "to_unix": 1662573600 }
      ]
    },
    {
      "availability": {
        "label": "Thursday, September 8th",
        "month": "September",
        "year": "2022",
        "day": "Thursday",
        "date": "08-09-2022",
        "available": 9,
        "unavailable": 0,
        "total": 9
      },
      "unavailable": [],
      "available": [
        { "from_unix": 1662624000, "to_unix": 1662642000 },
        { "from_unix": 1662645600, "to_unix": 1662660000 }
      ]
    },
    {
      "availability": {
        "label": "Friday, September 9th",
        "month": "September",
        "year": "2022",
        "day": "Friday",
        "date": "09-09-2022",
        "available": 7,
        "unavailable": 2,
        "total": 9
      },
      "unavailable": [
        { "from_unix": 1662710400, "to_unix": 1662714000 },
        { "from_unix": 1662735600, "to_unix": 1662739200 }
      ],
      "available": [
        { "from_unix": 1662710400, "to_unix": 1662728400 },
        { "from_unix": 1662732000, "to_unix": 1662746400 }
      ]
    },
    {
      "availability": {
        "label": "Saturday, September 10th",
        "month": "September",
        "year": "2022",
        "day": "Saturday",
        "date": "10-09-2022",
        "available": 6,
        "unavailable": 3,
        "total": 9
      },
      "unavailable": [
        { "from_unix": 1662822000, "to_unix": 1662825600 },
        { "from_unix": 1662804000, "to_unix": 1662807600 },
        { "from_unix": 1662804000, "to_unix": 1662807600 }
      ],
      "available": [
        { "from_unix": 1662796800, "to_unix": 1662814800 },
        { "from_unix": 1662818400, "to_unix": 1662832800 }
      ]
    },
    {
      "availability": {
        "label": "Sunday, September 11th",
        "month": "September",
        "year": "2022",
        "day": "Sunday",
        "date": "11-09-2022",
        "available": 7,
        "unavailable": 2,
        "total": 9
      },
      "unavailable": [
        { "from_unix": 1662890400, "to_unix": 1662894000 },
        { "from_unix": 1662904800, "to_unix": 1662908400 }
      ],
      "available": [
        { "from_unix": 1662883200, "to_unix": 1662901200 },
        { "from_unix": 1662904800, "to_unix": 1662919200 }
      ]
    },
    {
      "availability": {
        "label": "Monday, September 12th",
        "month": "September",
        "year": "2022",
        "day": "Monday",
        "date": "12-09-2022",
        "available": 6,
        "unavailable": 3,
        "total": 9
      },
      "unavailable": [
        { "from_unix": 1663002000, "to_unix": 1663005600 },
        { "from_unix": 1663002000, "to_unix": 1663005600 },
        { "from_unix": 1662994800, "to_unix": 1662998400 }
      ],
      "available": [
        { "from_unix": 1662969600, "to_unix": 1662987600 },
        { "from_unix": 1662991200, "to_unix": 1663005600 }
      ]
    },
    {
      "availability": {
        "label": "Tuesday, September 13th",
        "month": "September",
        "year": "2022",
        "day": "Tuesday",
        "date": "13-09-2022",
        "available": 7,
        "unavailable": 2,
        "total": 9
      },
      "unavailable": [
        { "from_unix": 1663081200, "to_unix": 1663084800 },
        { "from_unix": 1663081200, "to_unix": 1663084800 }
      ],
      "available": [
        { "from_unix": 1663056000, "to_unix": 1663074000 },
        { "from_unix": 1663077600, "to_unix": 1663092000 }
      ]
    },
    {
      "availability": {
        "label": "Wednesday, September 14th",
        "month": "September",
        "year": "2022",
        "day": "Wednesday",
        "date": "14-09-2022",
        "available": 6,
        "unavailable": 3,
        "total": 9
      },
      "unavailable": [
        { "from_unix": 1663146000, "to_unix": 1663149600 },
        { "from_unix": 1663156800, "to_unix": 1663160400 },
        { "from_unix": 1663174800, "to_unix": 1663178400 }
      ],
      "available": [
        { "from_unix": 1663142400, "to_unix": 1663160400 },
        { "from_unix": 1663164000, "to_unix": 1663178400 }
      ]
    },
    {
      "availability": {
        "label": "Thursday, September 15th",
        "month": "September",
        "year": "2022",
        "day": "Thursday",
        "date": "15-09-2022",
        "available": 7,
        "unavailable": 2,
        "total": 9
      },
      "unavailable": [
        { "from_unix": 1663257600, "to_unix": 1663261200 },
        { "from_unix": 1663250400, "to_unix": 1663254000 }
      ],
      "available": [
        { "from_unix": 1663228800, "to_unix": 1663246800 },
        { "from_unix": 1663250400, "to_unix": 1663264800 }
      ]
    },
    {
      "availability": {
        "label": "Friday, September 16th",
        "month": "September",
        "year": "2022",
        "day": "Friday",
        "date": "16-09-2022",
        "available": 6,
        "unavailable": 3,
        "total": 9
      },
      "unavailable": [
        { "from_unix": 1663340400, "to_unix": 1663344000 },
        { "from_unix": 1663315200, "to_unix": 1663318800 },
        { "from_unix": 1663329600, "to_unix": 1663333200 }
      ],
      "available": [
        { "from_unix": 1663315200, "to_unix": 1663333200 },
        { "from_unix": 1663336800, "to_unix": 1663351200 }
      ]
    },
    {
      "availability": {
        "label": "Saturday, September 17th",
        "month": "September",
        "year": "2022",
        "day": "Saturday",
        "date": "17-09-2022",
        "available": 9,
        "unavailable": 0,
        "total": 9
      },
      "unavailable": [],
      "available": [
        { "from_unix": 1663401600, "to_unix": 1663419600 },
        { "from_unix": 1663423200, "to_unix": 1663437600 }
      ]
    },
    {
      "availability": {
        "label": "Sunday, September 18th",
        "month": "September",
        "year": "2022",
        "day": "Sunday",
        "date": "18-09-2022",
        "available": 8,
        "unavailable": 1,
        "total": 9
      },
      "unavailable": [{ "from_unix": 1663498800, "to_unix": 1663502400 }],
      "available": [
        { "from_unix": 1663488000, "to_unix": 1663506000 },
        { "from_unix": 1663509600, "to_unix": 1663524000 }
      ]
    },
    {
      "availability": {
        "label": "Monday, September 19th",
        "month": "September",
        "year": "2022",
        "day": "Monday",
        "date": "19-09-2022",
        "available": 8,
        "unavailable": 1,
        "total": 9
      },
      "unavailable": [{ "from_unix": 1663578000, "to_unix": 1663581600 }],
      "available": [
        { "from_unix": 1663574400, "to_unix": 1663592400 },
        { "from_unix": 1663596000, "to_unix": 1663610400 }
      ]
    },
    {
      "availability": {
        "label": "Tuesday, September 20th",
        "month": "September",
        "year": "2022",
        "day": "Tuesday",
        "date": "20-09-2022",
        "available": 8,
        "unavailable": 1,
        "total": 9
      },
      "unavailable": [{ "from_unix": 1663671600, "to_unix": 1663675200 }],
      "available": [
        { "from_unix": 1663660800, "to_unix": 1663678800 },
        { "from_unix": 1663682400, "to_unix": 1663696800 }
      ]
    },
    {
      "availability": {
        "label": "Wednesday, September 21st",
        "month": "September",
        "year": "2022",
        "day": "Wednesday",
        "date": "21-09-2022",
        "available": 6,
        "unavailable": 3,
        "total": 9
      },
      "unavailable": [
        { "from_unix": 1663776000, "to_unix": 1663779600 },
        { "from_unix": 1663754400, "to_unix": 1663758000 },
        { "from_unix": 1663768800, "to_unix": 1663772400 }
      ],
      "available": [
        { "from_unix": 1663747200, "to_unix": 1663765200 },
        { "from_unix": 1663768800, "to_unix": 1663783200 }
      ]
    },
    {
      "availability": {
        "label": "Thursday, September 22nd",
        "month": "September",
        "year": "2022",
        "day": "Thursday",
        "date": "22-09-2022",
        "available": 8,
        "unavailable": 1,
        "total": 9
      },
      "unavailable": [{ "from_unix": 1663866000, "to_unix": 1663869600 }],
      "available": [
        { "from_unix": 1663833600, "to_unix": 1663851600 },
        { "from_unix": 1663855200, "to_unix": 1663869600 }
      ]
    },
    {
      "availability": {
        "label": "Friday, September 23rd",
        "month": "September",
        "year": "2022",
        "day": "Friday",
        "date": "23-09-2022",
        "available": 5,
        "unavailable": 4,
        "total": 9
      },
      "unavailable": [
        { "from_unix": 1663952400, "to_unix": 1663956000 },
        { "from_unix": 1663941600, "to_unix": 1663945200 },
        { "from_unix": 1663934400, "to_unix": 1663938000 },
        { "from_unix": 1663945200, "to_unix": 1663948800 }
      ],
      "available": [
        { "from_unix": 1663920000, "to_unix": 1663938000 },
        { "from_unix": 1663941600, "to_unix": 1663956000 }
      ]
    },
    {
      "availability": {
        "label": "Saturday, September 24th",
        "month": "September",
        "year": "2022",
        "day": "Saturday",
        "date": "24-09-2022",
        "available": 6,
        "unavailable": 3,
        "total": 9
      },
      "unavailable": [
        { "from_unix": 1664020800, "to_unix": 1664024400 },
        { "from_unix": 1664031600, "to_unix": 1664035200 },
        { "from_unix": 1664010000, "to_unix": 1664013600 }
      ],
      "available": [
        { "from_unix": 1664006400, "to_unix": 1664024400 },
        { "from_unix": 1664028000, "to_unix": 1664042400 }
      ]
    }
  ],
  "status": 200
}
